deprecate_kwargs/__init__.py
deprecate_kwargs/_dk.py
deprecate_kwargs/version.py
deprecate_kwargs-0.1.1.dist-info/METADATA
deprecate_kwargs-0.1.1.dist-info/WHEEL
deprecate_kwargs-0.1.1.dist-info/licenses/LICENSE
deprecate_kwargs-0.1.1.dist-info/RECORD
